algoai/__init__.py
algoai/a_star.py
algoai/alpha_beta.py
algoai/backward_chaining.py
algoai/bayesian_network.py
algoai/bfs.py
algoai/constraint_satisfaction_problem.py
algoai/cryptarithmetic.py
algoai/dfs.py
algoai/dpll_algo.py
algoai/eight_puzzle.py
algoai/forward_chaining.py
algoai/gbfs.py
algoai/iterative_deepening_search.py
algoai/memory_bounded_heuristic.py
algoai/minmax.py
algoai/n_queens.py
algoai/uniform_cost_search.py
algoai-0.2.5.dist-info/METADATA
algoai-0.2.5.dist-info/WHEEL
algoai-0.2.5.dist-info/top_level.txt
algoai-0.2.5.dist-info/RECORD
