Metadata-Version: 2.1
Name: algoai
Version: 0.2.5
Summary: A collection of AI algorithms
Author: Leander
Author-email: leander.antony2023@gmail.com
Classifier: Programming Language :: Python :: 3
Classifier: Operating System :: OS Independent
Requires-Python: >=3.6
Requires-Dist: numpy
Requires-Dist: networkx
Requires-Dist: pgmpy
